{
    "question_state_roi": [
        0.4349,
        0.3013,
        0.1327,
        0.1718
    ],
    "question": [
        0.3519,
        0.2169,
        0.2937,
        0.0917
    ],
    "answer_state_roi": [
        0.4033,
        0.6157,
        0.1926,
        0.2678
    ],
    "jump_1_button": [
        0.4015,
        0.6172,
        0.1943,
        0.0655
    ],
    "jump_5_button": [
        0.4024,
        0.7103,
        0.1935,
        0.0699
    ],
    "next_button": [
        0.4058,
        0.818,
        0.1901,
        0.0626
    ]
}